ToolboxDSA/__init__.py
ToolboxDSA/test.py
ToolboxDSA-0.0.3.dist-info/LICENSE
ToolboxDSA-0.0.3.dist-info/METADATA
ToolboxDSA-0.0.3.dist-info/WHEEL
ToolboxDSA-0.0.3.dist-info/top_level.txt
ToolboxDSA-0.0.3.dist-info/RECORD
